Metadata-Version: 2.1
Name: odoo-addon-l10n_us_partner_legal_number
Version: 18.0.1.0.0.2
Requires-Python: >=3.10
Requires-Dist: odoo==18.0.*
Requires-Dist: python-stdnum
Summary: Add Legal Number for North American Banking & Financials
Home-page: https://github.com/OCA/l10n-usa
License: AGPL-3
Author: Open Source Integrators, Odoo Community Association (OCA)
Author-email: support@odoo-community.org
Classifier: Programming Language :: Python
Classifier: Framework :: Odoo
Classifier: Framework :: Odoo :: 18.0
Classifier: License :: OSI Approved :: GNU Affero General Public License v3
